pipeflow/__init__.py
pipeflow/core/__init__.py
pipeflow/core/exceptions.py
pipeflow/core/pipeflow_action.py
pipeflow/core/pipeflow_context.py
pipeflow_lite-1.0.0.dist-info/LICENSE
pipeflow_lite-1.0.0.dist-info/METADATA
pipeflow_lite-1.0.0.dist-info/WHEEL
pipeflow_lite-1.0.0.dist-info/top_level.txt
pipeflow_lite-1.0.0.dist-info/RECORD
