Metadata-Version: 2.1
Name: pipeflow-lite
Version: 1.0.0
Summary: A flexible and powerful data processing pipeline library
Home-page: https://github.com/leonhoo/pipeflow-lite
Author: Leon
Author-email: leon.hooo@outlook.com
License: MIT License
Platform: all
Classifier: Intended Audience :: Developers
Classifier: Operating System :: OS Independent
Classifier: Natural Language :: Chinese (Simplified)
Classifier: Programming Language :: Python
Classifier: Topic :: Software Development :: Libraries
License-File: LICENSE
